kantanlog/__init__.py
kantanlog/apps.py
kantanlog/backends.py
kantanlog/decorators.py
kantanlog/middlewares.py
kantanlog/signals.py
tests/__init__.py
tests/models.py
tests/settings.py
tests/tests.py
tests/urls.py
tests/views.py
djangokantanlog-0.0.4.dist-info/LICENSE
djangokantanlog-0.0.4.dist-info/METADATA
djangokantanlog-0.0.4.dist-info/WHEEL
djangokantanlog-0.0.4.dist-info/top_level.txt
djangokantanlog-0.0.4.dist-info/RECORD
