Metadata-Version: 2.1
Name: djangokantanlog
Version: 0.0.4
Summary: Django helper app for logging ID.
Home-page: https://github.com/mmiyajima2/django-kantanlog
Author: Masafumi Miyajima
Author-email: mmiyajima2@gmail.com
License: UNKNOWN
Platform: UNKNOWN
Classifier: Environment :: Web Environment
Classifier: Framework :: Django
Classifier: Framework :: Django :: 2.0
Classifier: Framework :: Django :: 2.1
Classifier: Framework :: Django :: 2.2
Classifier: License :: OSI Approved :: MIT License
Classifier: Operating System :: OS Independent
Classifier: Programming Language :: Python
Classifier: Programming Language :: Python :: 3.6
Classifier: Programming Language :: Python :: 3.7
Requires-Dist: django
